unrest/__about__.py
unrest/__init__.py
unrest/coercers.py
unrest/rest.py
unrest/unrest.py
unrest/util.py
unrest/framework/__init__.py
unrest/framework/flask.py
unrest/framework/http_server.py
unrest/framework/sanic.py
unrest/framework/tornado.py
unrest/generators/__init__.py
unrest/generators/openapi.py
unrest/generators/options.py
unrest/idiom/__init__.py
unrest/idiom/json_server.py
unrest/idiom/unrest.py
unrest/idiom/yaml.py
unrest/tests/__init__.py
unrest/tests/conftest.py
unrest/tests/model.py
unrest/tests/test_coercers.py
unrest/tests/crud/__init__.py
unrest/tests/crud/test_delete.py
unrest/tests/crud/test_delete_pk.py
unrest/tests/crud/test_get.py
unrest/tests/crud/test_get_pk.py
unrest/tests/crud/test_patch.py
unrest/tests/crud/test_patch_pk.py
unrest/tests/crud/test_post.py
unrest/tests/crud/test_post_pk.py
unrest/tests/crud/test_put.py
unrest/tests/crud/test_put_pk.py
unrest/tests/features/__init__.py
unrest/tests/features/test_auth_decorators.py
unrest/tests/features/test_idiom.py
unrest/tests/features/test_misc.py
unrest/tests/features/test_paginated.py
unrest/tests/features/test_properties.py
unrest/tests/features/test_relationships.py
unrest/tests/features/test_validators.py
unrest/tests/helpers/__init__.py
unrest/tests/helpers/flask.py
unrest/tests/helpers/http_server.py
unrest/tests/helpers/sanic.py
unrest/tests/helpers/tornado.py
unrest/tests/helpers/unrest_client.py
unrest/tests/static/openapi_result.py
unrest-1.1.0.dist-info/WHEEL
unrest-1.1.0.dist-info/METADATA
unrest-1.1.0.dist-info/RECORD
