Metadata-Version: 2.1
Name: unrest
Version: 1.1.0
Summary: A troubling rest api library for sqlalchemy models
Keywords: rest,flask,api,sqlalchemy
Author-email: Florian Mounier <paradoxxx.zero@gmail.com>
Maintainer-email: Kozea <dev@kozea.fr>
Requires-Python: >=3.6
Classifier: Development Status :: 4 - Beta
Classifier: Environment :: Console
Classifier: Intended Audience :: End Users/Desktop
Classifier: License :: OSI Approved :: GNU Lesser General Public License v3 or later (LGPLv3+)
Classifier: Operating System :: OS Independent
Classifier: Programming Language :: Python :: 3
Requires-Dist: sqlalchemy
Requires-Dist: python-dateutil
Requires-Dist: pydoc-markdown<3.0 ; extra == "doc"
Requires-Dist: flask ; extra == "flask"
Requires-Dist: black ; extra == "test"
Requires-Dist: flake8 ; extra == "test"
Requires-Dist: pytest-cov ; extra == "test"
Requires-Dist: pytest-flake8 ; extra == "test"
Requires-Dist: pytest-isort ; extra == "test"
Requires-Dist: pytest ; extra == "test"
Requires-Dist: flask ; extra == "test"
Requires-Dist: flask-sqlalchemy ; extra == "test"
Requires-Dist: tornado ; extra == "test"
Requires-Dist: sanic<21 ; extra == "test"
Requires-Dist: aiohttp ; extra == "test"
Requires-Dist: pyyaml ; extra == "test"
Requires-Dist: tornado ; extra == "tornado"
Requires-Dist: pyyaml ; extra == "yaml"
Project-URL: Code, https://github.com/Kozea/unrest
Project-URL: Documentation, https://github.com/Kozea/unrest
Provides-Extra: doc
Provides-Extra: flask
Provides-Extra: test
Provides-Extra: tornado
Provides-Extra: yaml
